Metadata-Version: 2.1
Name: mimultiplicacion
Version: 0.4
Summary: Make a multiplicacion
Home-page: https://pypi.org/project/mimultiplicacion
Author: Juani
Author-email: juanita.agudelo@udea.edu.co
License: MIT
Keywords: multiplication maths
Platform: UNKNOWN
Classifier: Programming Language :: Python :: 3
Classifier: License :: OSI Approved :: MIT License
Classifier: Operating System :: OS Independent
License-File: LICENSE
